af_ibov_parser/__init__.py
af_ibov_parser/cli.py
af_ibov_parser/errors.py
af_ibov_parser/handlers.py
af_ibov_parser/parser.py
af_ibov_parser/record.py
af_ibov_parser/task.py
af_ibov_parser/version.py
af_ibov_parser-0.1.0.dist-info/entry_points.txt
af_ibov_parser-0.1.0.dist-info/LICENSE.md
af_ibov_parser-0.1.0.dist-info/WHEEL
af_ibov_parser-0.1.0.dist-info/METADATA
af_ibov_parser-0.1.0.dist-info/RECORD
