Metadata-Version: 2.1
Name: af-ibov-parser
Version: 0.1.0
Summary: fillme
License: MIT
Author: Leonardo Rossetti
Author-email: me@lrossetti.com
Requires-Python: >=3.9,<4.0
Classifier: License :: OSI Approved :: MIT License
Classifier: Programming Language :: Python :: 3
Requires-Dist: canonicaljson (>=1.4.0,<2.0.0)
